LICENSE.txt
mmlspark/__init__.py
mmlspark/automl/FindBestModel.py
mmlspark/automl/HyperparamBuilder.py
mmlspark/automl/TuneHyperparameters.py
mmlspark/automl/_FindBestModel.py
mmlspark/automl/_TuneHyperparameters.py
mmlspark/automl/__init__.py
mmlspark/cntk/CNTKModel.py
mmlspark/cntk/_CNTKModel.py
mmlspark/cntk/__init__.py
mmlspark/cognitive/AddDocuments.py
mmlspark/cognitive/AnalyzeImage.py
mmlspark/cognitive/AzureSearchWriter.py
mmlspark/cognitive/BingImageSearch.py
mmlspark/cognitive/DescribeImage.py
mmlspark/cognitive/DetectAnomalies.py
mmlspark/cognitive/DetectFace.py
mmlspark/cognitive/DetectLastAnomaly.py
mmlspark/cognitive/EntityDetector.py
mmlspark/cognitive/FindSimilarFace.py
mmlspark/cognitive/GenerateThumbnails.py
mmlspark/cognitive/GroupFaces.py
mmlspark/cognitive/IdentifyFaces.py
mmlspark/cognitive/KeyPhraseExtractor.py
mmlspark/cognitive/LanguageDetector.py
mmlspark/cognitive/NER.py
mmlspark/cognitive/OCR.py
mmlspark/cognitive/RecognizeDomainSpecificContent.py
mmlspark/cognitive/RecognizeText.py
mmlspark/cognitive/SimpleDetectAnomalies.py
mmlspark/cognitive/SpeechToText.py
mmlspark/cognitive/SpeechToTextSDK.py
mmlspark/cognitive/TagImage.py
mmlspark/cognitive/TextSentiment.py
mmlspark/cognitive/VerifyFaces.py
mmlspark/cognitive/_BingImageSearch.py
mmlspark/cognitive/__init__.py
mmlspark/core/__init__.py
mmlspark/core/schema/TypeConversionUtils.py
mmlspark/core/schema/Utils.py
mmlspark/core/schema/__init__.py
mmlspark/core/serialize/__init__.py
mmlspark/core/serialize/java_params_patch.py
mmlspark/core/spark/FluentAPI.py
mmlspark/core/spark/__init__.py
mmlspark/doc/__init__.py
mmlspark/doc/conf.py
mmlspark/downloader/ModelDownloader.py
mmlspark/downloader/__init__.py
mmlspark/featurize/AssembleFeatures.py
mmlspark/featurize/CleanMissingData.py
mmlspark/featurize/DataConversion.py
mmlspark/featurize/Featurize.py
mmlspark/featurize/IndexToValue.py
mmlspark/featurize/ValueIndexer.py
mmlspark/featurize/ValueIndexerModel.py
mmlspark/featurize/__init__.py
dcborow_mmlspark-0.14.dev1.dist-info/LICENSE.txt
dcborow_mmlspark-0.14.dev1.dist-info/METADATA
dcborow_mmlspark-0.14.dev1.dist-info/WHEEL
dcborow_mmlspark-0.14.dev1.dist-info/top_level.txt
dcborow_mmlspark-0.14.dev1.dist-info/zip-safe
dcborow_mmlspark-0.14.dev1.dist-info/RECORD
